<?xml version="1.0" encoding="utf-8" ?><dwsync><file name="amanoya.png" server="sv2.html.xdomain.ne.jp" local="3587829570" remote="3588029640" Dst="-1" /><file name="amanoya_2.png" server="sv2.html.xdomain.ne.jp" local="3579989876" remote="3588029640" Dst="-1" /><file name="blackbox.png" server="sv2.html.xdomain.ne.jp" local="3579993305" remote="3588029640" Dst="-1" /><file name="blackbox_2.png" server="sv2.html.xdomain.ne.jp" local="3579993503" remote="3588029640" Dst="-1" /><file name="clue_logo.jpg" server="sv2.html.xdomain.ne.jp" local="3587696202" remote="3588029640" Dst="-1" /><file name="clue_logo.png" server="sv2.html.xdomain.ne.jp" local="3587695732" remote="3588029640" Dst="-1" /><file name="clue_web.png" server="sv2.html.xdomain.ne.jp" local="3587695471" remote="3588029640" Dst="-1" /><file name="edomono.jpg" server="sv2.html.xdomain.ne.jp" local="3579996999" remote="3588029640" Dst="-1" /><file name="edomono_2.jpg" server="sv2.html.xdomain.ne.jp" local="3579996840" remote="3588029640" Dst="-1" /><file name="icon.jpg" server="sv2.html.xdomain.ne.jp" local="3579732960" remote="3588029640" Dst="-1" /><file name="inQ.png" server="sv2.html.xdomain.ne.jp" local="3587829592" remote="3588029640" Dst="-1" /><file name="inQ_2.png" server="sv2.html.xdomain.ne.jp" local="3579990399" remote="3588029640" Dst="-1" /><file name="photo_1.jpg" server="sv2.html.xdomain.ne.jp" local="3579814765" remote="3588029640" Dst="-1" /><file name="photo_10.jpg" server="sv2.html.xdomain.ne.jp" local="3579815547" remote="3588029640" Dst="-1" /><file name="photo_11.jpg" server="sv2.html.xdomain.ne.jp" local="3579815590" remote="3588029640" Dst="-1" /><file name="photo_12.JPG" server="sv2.html.xdomain.ne.jp" local="3579815684" remote="3588029640" Dst="-1" /><file name="photo_13.jpg" server="sv2.html.xdomain.ne.jp" local="3579815726" remote="3588029640" Dst="-1" /><file name="photo_14.jpg" server="sv2.html.xdomain.ne.jp" local="3579815756" remote="3588029640" Dst="-1" /><file name="photo_15.JPG" server="sv2.html.xdomain.ne.jp" local="3579815818" remote="3588029640" Dst="-1" /><file name="photo_16.jpg" server="sv2.html.xdomain.ne.jp" local="3579815855" remote="3588029640" Dst="-1" /><file name="photo_2.jpg" server="sv2.html.xdomain.ne.jp" local="3579814999" remote="3588029640" Dst="-1" /><file name="photo_3.JPG" server="sv2.html.xdomain.ne.jp" local="3579815070" remote="3588029640" Dst="-1" /><file name="photo_4.jpg" server="sv2.html.xdomain.ne.jp" local="3579815147" remote="3588029640" Dst="-1" /><file name="photo_5.jpg" server="sv2.html.xdomain.ne.jp" local="3579815232" remote="3588029640" Dst="-1" /><file name="photo_6.jpg" server="sv2.html.xdomain.ne.jp" local="3579815317" remote="3588029640" Dst="-1" /><file name="photo_7.jpg" server="sv2.html.xdomain.ne.jp" local="3579815399" remote="3588029700" Dst="-1" /><file name="photo_8.JPG" server="sv2.html.xdomain.ne.jp" local="3579815440" remote="3588029700" Dst="-1" /><file name="photo_9.JPG" server="sv2.html.xdomain.ne.jp" local="3579815495" remote="3588029700" Dst="-1" /><file name="top.jpg" server="sv2.html.xdomain.ne.jp" local="3579923767" remote="3588029700" Dst="-1" /><file name="top.png" server="sv2.html.xdomain.ne.jp" local="3579923822" remote="3588029700" Dst="-1" /><file name="typeface.png" server="sv2.html.xdomain.ne.jp" local="3579994793" remote="3588029700" Dst="-1" /><file name="typeface_2.png" server="sv2.html.xdomain.ne.jp" local="3579995123" remote="3588029700" Dst="-1" /><file name="wf_index.jpg" server="sv2.html.xdomain.ne.jp" local="3587829598" remote="3588029700" Dst="-1" /><file name="wf_logo.png" server="sv2.html.xdomain.ne.jp" local="3579988898" remote="3588029700" Dst="-1" /></dwsync>